torchfold/__init__.py
torchfold/torchfold.py
torchfold/torchfold_test.py
torchfold-0.1.0.dist-info/METADATA
torchfold-0.1.0.dist-info/RECORD
torchfold-0.1.0.dist-info/WHEEL
torchfold-0.1.0.dist-info/top_level.txt
