Metadata-Version: 2.1
Name: torchfold
Version: 0.1.0
Summary: Dynamic Batching with PyTorch
Home-page: UNKNOWN
Author: Illia Polosukhin, NEAR Inc
Author-email: illia@near.ai
License: Apache License, Version 2.0
Project-URL: Blog Post, http://near.ai/articles/2017-09-06-PyTorch-Dynamic-Batching/
Project-URL: Source, https://github.com/nearai/torchfold
Platform: UNKNOWN
